potatoscript/potatoPostgreSQL.py
potatoscript/test.py
python/potatoPostgreSQL.py
python/pyPostgreSQL.py
python/xMySQL.py
python/xOracle.py
python/xPostgreSQL.py
xOracle-1.0.3.dist-info/METADATA
xOracle-1.0.3.dist-info/WHEEL
xOracle-1.0.3.dist-info/top_level.txt
xOracle-1.0.3.dist-info/RECORD
