Metadata-Version: 2.1
Name: xOracle
Version: 1.0.3
Summary: A simple library for connecting to Oracle
Author: ks lim
Author-email: kianseng.lim@sony.com
